countdown/__init__.py
countdown/ca1_model_answer.py
countdown/model_ans_test.py
countdown_pkg_mcollison-0.0.6.dist-info/LICENSE
countdown_pkg_mcollison-0.0.6.dist-info/METADATA
countdown_pkg_mcollison-0.0.6.dist-info/WHEEL
countdown_pkg_mcollison-0.0.6.dist-info/top_level.txt
countdown_pkg_mcollison-0.0.6.dist-info/RECORD
