Metadata-Version: 2.1
Name: countdown-pkg-mcollison
Version: 0.0.6
Summary: A simulation of the countdown game show used for demonstration.
Home-page: https://github.com/mcollison/CA1-countdown
Author: Matt Collison
Author-email: m.collison@exeter.ac.uk
License: UNKNOWN
Platform: UNKNOWN
Classifier: Programming Language :: Python :: 3
Classifier: License :: OSI Approved :: MIT License
Classifier: Operating System :: OS Independent
Requires-Python: >=3.6
